fieldz/__init__.py
fieldz/_functions.py
fieldz/_repr.py
fieldz/_types.py
fieldz/py.typed
fieldz/adapters/__init__.py
fieldz/adapters/_attrs.py
fieldz/adapters/_dataclasses.py
fieldz/adapters/_dataclassy.py
fieldz/adapters/_msgspec.py
fieldz/adapters/_named_tuple.py
fieldz/adapters/_pydantic.py
fieldz/adapters/_typed_dict.py
fieldz/adapters/protocol.py
fieldz-0.1.3.dist-info/METADATA
fieldz-0.1.3.dist-info/WHEEL
fieldz-0.1.3.dist-info/licenses/LICENSE
fieldz-0.1.3.dist-info/RECORD
