Metadata-Version: 2.4
Name: fieldz
Version: 0.1.3
Summary: Utilities for providing compatibility with many dataclass-like libraries
Project-URL: homepage, https://github.com/pyapp-kit/fieldz
Project-URL: repository, https://github.com/pyapp-kit/fieldz
Author-email: Talley Lambert <talley.lambert@gmail.com>
License: BSD-3-Clause
License-File: LICENSE
Classifier: Development Status :: 3 - Alpha
Classifier: License :: OSI Approved :: BSD License
Classifier: Programming Language :: Python :: 3
Classifier: Programming Language :: Python :: 3.8
Classifier: Programming Language :: Python :: 3.9
Classifier: Programming Language :: Python :: 3.10
Classifier: Programming Language :: Python :: 3.11
Classifier: Programming Language :: Python :: 3.12
Classifier: Typing :: Typed
Requires-Python: >=3.8
Requires-Dist: typing-extensions
Provides-Extra: dev
Requires-Dist: hatch; extra == 'dev'
Requires-Dist: ipython; extra == 'dev'
Requires-Dist: mypy; extra == 'dev'
Requires-Dist: pdbpp; extra == 'dev'
Requires-Dist: pre-commit-uv; extra == 'dev'
Requires-Dist: rich; extra == 'dev'
Requires-Dist: ruff; extra == 'dev'
Provides-Extra: test
Requires-Dist: annotated-types; extra == 'test'
Requires-Dist: attrs; extra == 'test'
Requires-Dist: dataclassy; extra == 'test'
Requires-Dist: msgspec; extra == 'test'
Requires-Dist: pydantic; extra == 'test'
Requires-Dist: pytest; extra == 'test'
Requires-Dist: pytest-cov; extra == 'test'
